pysss2/__init__.py
pysss2/geomPlotter.py
pysss2/icon.png
pysss2/libsss2.py
pysss2/plots.py
pysss2/pysss2.py
pysss2/slicer.py
pysss2-0.4.1.data/scripts/pysss2
pysss2-0.4.1.dist-info/LICENSE
pysss2-0.4.1.dist-info/METADATA
pysss2-0.4.1.dist-info/WHEEL
pysss2-0.4.1.dist-info/top_level.txt
pysss2-0.4.1.dist-info/RECORD
