Metadata-Version: 2.1
Name: pysss2
Version: 0.4.1
Summary: Tools to interact with the Serpent2 Monte Carlo code
Home-page: https://github.com/sjjamsa/pysss2
Author: Simppa Äkäslompolo
Author-email: simppa.akaslompolo@alumni.aalto.fi
License: UNKNOWN
Platform: UNKNOWN
Classifier: Programming Language :: Python :: 3
Classifier: License :: OSI Approved :: GNU General Public License v3 (GPLv3)
Classifier: Operating System :: POSIX :: Linux
Classifier: Development Status :: 3 - Alpha
Requires-Python: >=3.6.7
Requires-Dist: matplotlib (>=3.1.1)
